torch_jax_interop/__init__.py
torch_jax_interop/conftest.py
torch_jax_interop/docs_test.py
torch_jax_interop/py.typed
torch_jax_interop/to_jax.py
torch_jax_interop/to_jax_module.py
torch_jax_interop/to_jax_module_test.py
torch_jax_interop/to_jax_test.py
torch_jax_interop/to_torch.py
torch_jax_interop/to_torch_module.py
torch_jax_interop/to_torch_module_test.py
torch_jax_interop/to_torch_test.py
torch_jax_interop/types.py
torch_jax_interop/utils.py
torch_jax_interop-0.0.8.dist-info/METADATA
torch_jax_interop-0.0.8.dist-info/WHEEL
torch_jax_interop-0.0.8.dist-info/licenses/LICENSE
torch_jax_interop-0.0.8.dist-info/RECORD
