Metadata-Version: 2.4
Name: torch_jax_interop
Version: 0.0.8
Summary: Simple tools to mix and match PyTorch and Jax - Get the best of both worlds!
Author-email: Fabrice Normandin <fabrice.normandin@gmail.com>
License-File: LICENSE
Requires-Python: >=3.11
Requires-Dist: jax>=0.6.0
Requires-Dist: setuptools; python_version == '3.11'
Requires-Dist: torch
Provides-Extra: gpu
Requires-Dist: jax[cuda13]; (sys_platform == 'linux') and extra == 'gpu'
